ebops-0.3.7.dist-info/METADATA
ebops-0.3.7.dist-info/WHEEL
ebops-0.3.7.dist-info/entry_points.txt
ebops-0.3.7.dist-info/licenses/LICENSE
ebops/__init__.py
ebops/adapters/__init__.py
ebops/adapters/anki.py
ebops/entrypoints/__init__.py
ebops/entrypoints/cli.py
ebops/entrypoints/utils.py
ebops/exceptions.py
ebops/model.py
ebops/py.typed
ebops/services.py
ebops/version.py
ebops-0.3.7.dist-info/RECORD
