Metadata-Version: 2.1
Name: ebops
Version: 0.3.7
Summary: Manage e-book and org files to make analytical reading easy
Author-Email: Lyz <lyz@riseup.net>
License: GPL-3.0-only
Classifier: Development Status :: 2 - Pre-Alpha
Classifier: Intended Audience :: Developers
Classifier: License :: OSI Approved :: GNU General Public License v3 (GPLv3)
Classifier: Operating System :: Unix
Classifier: Operating System :: POSIX
Classifier: Programming Language :: Python
Classifier: Programming Language :: Python :: 3
Classifier: Programming Language :: Python :: 3.8
Classifier: Programming Language :: Python :: 3.9
Classifier: Programming Language :: Python :: 3.10
Classifier: Programming Language :: Python :: 3.11
Classifier: Topic :: Utilities
Classifier: Natural Language :: English
Project-URL: Issues, https://codeberg.org/lyz/ebops/issues
Project-URL: homepage, https://codeberg.org/lyz/ebops
Requires-Python: >=3.9.2
Requires-Dist: typer[all]>=0.9.0
Requires-Dist: org-rw>=0.0.2
Requires-Dist: ebooklib>=0.18
Requires-Dist: beautifulsoup4>=4.13.0b2
Requires-Dist: lxml>=5.2.2
Requires-Dist: pydantic>=2.8.2
Requires-Dist: requests>=2.32.3
